rumor_view/__init__.py
rumor_view/categoricalization.py
rumor_view/view.py
rumor_view-0.0.3.dist-info/METADATA
rumor_view-0.0.3.dist-info/WHEEL
rumor_view-0.0.3.dist-info/top_level.txt
rumor_view-0.0.3.dist-info/RECORD
