Metadata-Version: 2.1
Name: rumor-view
Version: 0.0.3
Summary: Visualization of column value relationship
Home-page: https://github.com/not-so-fat/rumor_view
Author: @not-so-fat
Author-email: conjurer.not.so.fat@gmail.com
Classifier: Programming Language :: Python :: 3
Classifier: License :: OSI Approved :: MIT License
Classifier: Operating System :: OS Independent
Requires-Python: >=3.6
Requires-Dist: numpy
Requires-Dist: pandas
Requires-Dist: scipy
Requires-Dist: networkx
Requires-Dist: pyvis
